openschema/__init__.py
openschema/kaggle/__init__.py
openschema/kaggle/_avazu.py
openschema/kaggle/_titanic.py
openschema/sklearn/__init__.py
openschema/sklearn/_breast_cancer.py
openschema/sklearn/_iris.py
openschema-0.7.dist-info/METADATA
openschema-0.7.dist-info/WHEEL
openschema-0.7.dist-info/licenses/LICENSE
openschema-0.7.dist-info/licenses/NOTICE
openschema-0.7.dist-info/RECORD
